fastsl/__init__.py
fastsl/fastsl_cli.py
fastsl/genes.py
fastsl/parallel_genes.py
fastsl/parallel_rxns.py
fastsl/rxns.py
fastsl-0.1.2.dist-info/DESCRIPTION.rst
fastsl-0.1.2.dist-info/METADATA
fastsl-0.1.2.dist-info/RECORD
fastsl-0.1.2.dist-info/WHEEL
fastsl-0.1.2.dist-info/entry_points.txt
fastsl-0.1.2.dist-info/metadata.json
fastsl-0.1.2.dist-info/top_level.txt
tests/__init__.py
tests/test_multi_core.py
tests/test_single_core.py
