Metadata-Version: 2.0
Name: fastsl
Version: 0.1.2
Summary: FastSL-py is an efficient algorithm to identify synthetic lethal gene/reaction sets in genome-scale metabolic models.
Home-page: https://github.com/RamanLab/FastSL-py
Author: Synchon Mandal, Karthik Raman
Author-email: fast-sl@ramanlab.groups.io
Maintainer: Synchon Mandal
Maintainer-email: synchonmandal@gmail.com
License: GPL v3
Project-URL: Source, https://github.com/RamanLab/FastSL-py
Keywords: synthetic-lethals flux-balance-analysis linear-programming computational-systems-biology
Platform: GNU/Linux
Platform: macOS >= 10.7
Platform: Microsoft Windows >= 7
Classifier: Development Status :: 4 - Beta
Classifier: Intended Audience :: Science/Research
Classifier: Topic :: Scientific/Engineering :: Bio-Informatics
Classifier: Environment :: Console
Classifier: License :: OSI Approved :: GNU General Public License v3 or later (GPLv3+)
Classifier: Programming Language :: Python
Classifier: Programming Language :: Python :: 3.5
Classifier: Programming Language :: Python :: 3.6
Requires-Python: ~=3.5
Requires-Dist: Click
Requires-Dist: cobra
Requires-Dist: joblib
Requires-Dist: lxml
Requires-Dist: tqdm
